django_choice_object/__init__.py
django_choice_object/choice.py
django_choice_object-0.9.dist-info/DESCRIPTION.rst
django_choice_object-0.9.dist-info/METADATA
django_choice_object-0.9.dist-info/RECORD
django_choice_object-0.9.dist-info/WHEEL
django_choice_object-0.9.dist-info/metadata.json
django_choice_object-0.9.dist-info/top_level.txt
