Metadata-Version: 2.0
Name: django-choice-object
Version: 0.9
Summary: A choice object for Django forms and models
Home-page: https://github.com/orf/django-choice-object
Author: Tom
Author-email: tom@tomforb.es
License: UNKNOWN
Platform: UNKNOWN
Requires-Dist: six
